api_investment_risk/__init__.py
api_investment_risk/data.py
api_investment_risk/datamart.py
api_investment_risk-0.3.9.6.dist-info/METADATA
api_investment_risk-0.3.9.6.dist-info/WHEEL
api_investment_risk-0.3.9.6.dist-info/top_level.txt
api_investment_risk-0.3.9.6.dist-info/RECORD
