Metadata-Version: 2.1
Name: api-investment-risk
Version: 0.3.9.6
Summary: UNKNOWN
Home-page: UNKNOWN
License: UNKNOWN
Platform: UNKNOWN
Requires-Dist: pandas>=2.2.3
Requires-Dist: requests>=2.32.3
